tacc-0.1.0.dist-info/METADATA
tacc-0.1.0.dist-info/WHEEL
tacc-0.1.0.dist-info/licenses/LICENSE
tacc/__init__.py
tacc/__pycache__/__init__.cpython-312.pyc
tacc/_internal.abi3.so
tacc/py.typed
tacc-0.1.0.dist-info/RECORD
