Metadata-Version: 2.4
Name: tacc
Version: 0.1.0
Classifier: Development Status :: 4 - Beta
Classifier: Intended Audience :: Developers
Classifier: License :: OSI Approved :: MIT License
Classifier: Programming Language :: Rust
Classifier: Programming Language :: Python :: Implementation :: CPython
Classifier: Programming Language :: Python :: 3.9
Classifier: Programming Language :: Python :: 3.10
Classifier: Programming Language :: Python :: 3.11
Classifier: Programming Language :: Python :: 3.12
Classifier: Topic :: Software Development :: Libraries
Classifier: Topic :: System :: Archiving :: Compression
License-File: LICENSE
Summary: High-performance token compression for LLMs with Rust-backed implementation
Keywords: compression,tokens,llm,thrift,rust
Author: Elijah Kurien
License: MIT
Requires-Python: >=3.9
Project-URL: Homepage, https://github.com/elijah0528/tacc
Project-URL: Repository, https://github.com/elijah0528/tacc
Project-URL: Issues, https://github.com/elijah0528/tacc/issues
